{"users":[{"id":2,"username":"omid","email":"omid.leo2014@gmail.com","password":"omid1010"},{"id":5,"username":"reza","email":"reza.leo2014@gmail.com","password":"reza1010"},{"id":"02877ad1-c73a-4088-98ad-3bcba201d9ad","username":"mohaddese","email":"mohaddese@gmail.com","password":"mohaddese2020"},{"id":"kgkshgkshgkshgls0","username":"davood","email":"davood@gmail.com","password":"davood2020"},{"id":"f13a5306-a620-41e4-9aae-28d018716c20","username":"hoda","email":"hoda@gmail.com","password":"hoda1010"},{"id":"62a76b5a-02d3-48b6-a7a8-133df22e0233","username":"shima","email":"shima@gmail.com","password":"shims2020"},{"id":"4a9e2a9f-816b-400f-92ff-df4ffc8e50c2","username":"hasan","email":"hasan@gmail.com","password":"hasan1011"},{"id":"939c7fdc-7900-4848-a463-bcd092a8300f","username":"kukugkuguk","email":"jyfyjflj@gmail.com","password":".ukgug6r6fh"}]}